{"cameraMode":{"drawMode":0,"name":"Shaded","section":"Shading Mode"},"sceneLighting":true,"audioPlay":false,"sceneViewState":{"showFog":true,"showMaterialUpdate":false,"showSkybox":true,"showFlares":true,"showImageEffects":true,"showParticleSystems":true},"in2DMode":false,"pivot":{"x":-42.637733459472659,"y":-7.6338653564453129,"z":80.49578857421875},"rotation":{"x":-0.24928151071071626,"y":0.49356240034103396,"z":-0.15407249331474305,"w":-0.8192383050918579},"size":111.53218841552735,"orthographic":false}